api/routers/__init__.py
api/routers/cryptocurrency.py
api/routers/exchange.py
api/routers/nft.py
api/utils/__init__.py
api/utils/config.py
api/utils/database.py
api/utils/schemas.py
cmc/__init__.py
cmc/modules/__init__.py
cmc/modules/base.py
cmc/modules/cryptocurrency/__init__.py
cmc/modules/cryptocurrency/currency.py
cmc/modules/cryptocurrency/gainers.py
cmc/modules/cryptocurrency/losers.py
cmc/modules/cryptocurrency/most_visited.py
cmc/modules/cryptocurrency/price_prediction.py
cmc/modules/cryptocurrency/ranking.py
cmc/modules/cryptocurrency/recently_added.py
cmc/modules/cryptocurrency/trending.py
cmc/modules/exchange/__init__.py
cmc/modules/exchange/derivatives.py
cmc/modules/exchange/dex.py
cmc/modules/exchange/exchange.py
cmc/modules/exchange/lending.py
cmc/modules/exchange/spot.py
cmc/modules/nft/__init__.py
cmc/modules/nft/airdrop.py
cmc/modules/nft/collection.py
cmc/modules/nft/upcoming.py
cmc/resources/__init__.py
cmc/resources/user_agents.py
cmc/utils/__init__.py
cmc/utils/exceptions.py
cmc/utils/format.py
cmc/utils/models.py
tests/api/__init__.py
tests/api/test_main.py
tests/api/routers/__init__.py
tests/api/routers/test_cryptocurrency.py
tests/api/routers/test_exchange.py
tests/api/routers/test_nft.py
tests/api/utils/__init__.py
tests/api/utils/test_config.py
tests/api/utils/test_database.py
tests/cmc/__init__.py
tests/cmc/cryptocurrency/__init__.py
tests/cmc/cryptocurrency/test_currency.py
tests/cmc/cryptocurrency/test_gainers.py
tests/cmc/cryptocurrency/test_losers.py
tests/cmc/cryptocurrency/test_most_visited.py
tests/cmc/cryptocurrency/test_price_prediction.py
tests/cmc/cryptocurrency/test_ranking.py
tests/cmc/cryptocurrency/test_recently_added.py
tests/cmc/cryptocurrency/test_trending.py
tests/cmc/exchange/__init__.py
tests/cmc/exchange/test_derivatives.py
tests/cmc/exchange/test_dex.py
tests/cmc/exchange/test_exchange.py
tests/cmc/exchange/test_lending.py
tests/cmc/exchange/test_spot.py
tests/cmc/nft/__init__.py
tests/cmc/nft/test_airdrop.py
cmc_py_wrapper-0.1.4.dist-info/LICENSE
cmc_py_wrapper-0.1.4.dist-info/METADATA
cmc_py_wrapper-0.1.4.dist-info/WHEEL
cmc_py_wrapper-0.1.4.dist-info/top_level.txt
cmc_py_wrapper-0.1.4.dist-info/RECORD
