Metadata-Version: 2.1
Name: cmc-py-wrapper
Version: 0.1.4
Summary: Unofficial CoinMarketCap API and Python wrapper
Home-page: https://devansh3712.github.io/cmc-py/
Author: Devansh Singh
Author-email: devanshamity@gmail.com
License: MIT
Download-URL: https://pypi.org/project/cmc-py-wrapper/
Project-URL: Source, https://github.com/Devansh3712/cmc-py
Project-URL: Documentation, https://devansh3712.github.io/cmc-py/
Platform: UNKNOWN
Classifier: Programming Language :: Python :: 3.9
Classifier: Programming Language :: Python :: 3.10
Classifier: License :: OSI Approved :: MIT License
Classifier: Operating System :: Microsoft :: Windows
License-File: LICENSE
Requires-Dist: async-generator (==1.10)
Requires-Dist: attrs (==21.4.0)
Requires-Dist: beautifulsoup4 (==4.10.0)
Requires-Dist: certifi (==2021.10.8)
Requires-Dist: cffi (==1.15.0)
Requires-Dist: charset-normalizer (==2.0.12)
Requires-Dist: colorama (==0.4.4)
Requires-Dist: configparser (==5.2.0)
Requires-Dist: crayons (==0.4.0)
Requires-Dist: cryptography (==36.0.1)
Requires-Dist: h11 (==0.13.0)
Requires-Dist: idna (==3.3)
Requires-Dist: lxml (==4.8.0)
Requires-Dist: outcome (==1.1.0)
Requires-Dist: pycparser (==2.21)
Requires-Dist: pyOpenSSL (==22.0.0)
Requires-Dist: requests (==2.27.1)
Requires-Dist: selenium (==4.1.0)
Requires-Dist: sniffio (==1.2.0)
Requires-Dist: sortedcontainers (==2.4.0)
Requires-Dist: soupsieve (==2.3.1)
Requires-Dist: trio (==0.19.0)
Requires-Dist: trio-websocket (==0.9.2)
Requires-Dist: urllib3 (==1.26.8)
Requires-Dist: webdriver-manager (==3.5.3)
Requires-Dist: wsproto (==1.0.0)
